[
    {
      "uri": "http:\/\/repository.lppm.unila.ac.id\/id\/eprint\/6055",
      "type": "article",
      "volume": 1,
      "subjects": [
        "F001"
      ],
      "metadata_visibility": "show",
      "title": "PEMANFAATAN MEDIA AUDIO VISUAL UNTUK MENINGKATKAN AKTIVITAS SISWA DAN KETERAMPILAN BERBICARA (BEBALAH)",
      "related_url": [
        {
          "type": "author",
          "url": "http:\/\/jurnal.fkip.unila.ac.id\/index.php\/JTL\/article\/view\/12517"
        }
      ],
      "publication": "PEMANFAATAN MEDIA AUDIO VISUAL UNTUK MENINGKATKAN AKTIVITAS SISWA DAN KETERAMPILAN BERBICARA (BEBALAH)",
      "date": 2017,
      "documents": [
          {
            "uri": "http:\/\/repository.lppm.unila.ac.id\/id\/document\/18970",
            "rev_number": 3,
            "files": [
                {
                  "filename": 12517,
                  "hash_type": "MD5",
                  "mime_type": "application\/xml",
                  "objectid": 18970,
                  "datasetid": "document",
                  "hash": "455a44c69668c87855c99a45bb9928eb",
                  "mtime": "2017-11-20 09:09:36",
                  "fileid": 55881,
                  "filesize": 19165,
                  "uri": "http:\/\/repository.lppm.unila.ac.id\/id\/file\/55881"
                }
            ],
            "pos": 1,
            "eprintid": 6055,
            "language": "id",
            "main": 12517,
            "format": "text",
            "placement": 1,
            "security": "staffonly",
            "mime_type": "application\/xml",
            "docid": 18970
          }
      ],
      "userid": 849,
      "status_changed": "2018-04-26 02:03:18",
      "official_url": "http:\/\/jurnal.fkip.unila.ac.id\/index.php\/JTL\/article\/view\/12517",
      "full_text_status": "restricted",
      "publisher": "Universitas Lampung",
      "rev_number": 8,
      "creators": [
        {
          "id": null,
          "name": {
            "lineage": null,
            "honourific": null,
            "family": "Rulia, Masturi",
            "given": "Rulia"
          }
        },
        {
          "name": {
            "family": "Suyanto, Edi",
            "given": "Edi",
            "honourific": null,
            "lineage": null
          },
          "id": "doktor_edy@yahoo.com"
        },
        {
          "name": {
            "honourific": null,
            "lineage": null,
            "given": "Iqbal",
            "family": "Hilal, Iqbal"
          },
          "id": null
        }
      ],
      "eprintid": 6055,
      "lastmod": "2018-04-26 02:03:18",
      "number": 1,
      "refereed": "TRUE",
      "date_type": "published",
      "eprint_status": "archive",
      "abstract": "This research was a classroom action research conducted in class VII Junior High School Islamiyah Bandar Lampung in academic year 2015-2016 which aimed to improve learning outcomes and speaking skills (bebalah). The results showed an increase in activity and skill (bebalah) students in class VII Junior High School Islamiyah Bandar Lampung in each cycle. The first cycle of student activity in the category of less then into the category of good in the second cycle. Bebalahan ability levels of students in the first cycle the average value of the acquisition of 53.3% in the category of less and skill levels of students increased to well with a mean value of 83.3% in the second cycle to be better. This proves that the used of audio-visual media such as video can increase the activity and speaking skills (bebalah) on a class VII Junior High School Islamiyah Bandar Lampung in lessons year 2015-2016.Kata kunci: media audiovisual, aktivitas hasil  belajar, keterampilan berbicara",
      "ispublished": "pub",
      "divisions": [
        "FKIP8"
      ],
      "dir": "disk0\/00\/00\/60\/55",
      "datestamp": "2018-04-26 02:03:18"
    }
]

